yucebio_uploader/__init__.py
yucebio_uploader/ali.py
yucebio_uploader/aws.py
yucebio_uploader/base.py
yucebio_uploader/commands.py
Yucebio_Uploader-0.1.1.dist-info/METADATA
Yucebio_Uploader-0.1.1.dist-info/WHEEL
Yucebio_Uploader-0.1.1.dist-info/entry_points.txt
Yucebio_Uploader-0.1.1.dist-info/top_level.txt
Yucebio_Uploader-0.1.1.dist-info/RECORD
