Metadata-Version: 2.1
Name: Yucebio-Uploader
Version: 0.1.1
Summary: 通用数据上传工具
Home-page: UNKNOWN
Author: huangqingjun
Author-email: huangqingjun@yucebio.com
License: MIT
Platform: UNKNOWN
Classifier: License :: OSI Approved :: MIT License
Classifier: Programming Language :: Python
Classifier: Programming Language :: Python :: 3
Classifier: Programming Language :: Python :: 3.8
Classifier: Programming Language :: Python :: Implementation :: CPython
Classifier: Programming Language :: Python :: Implementation :: PyPy
Requires-Python: >=3.8
Requires-Dist: click
Requires-Dist: oss2
Requires-Dist: Yucebio-Config
